esrt/__init__.py
esrt/__main__.py
esrt/__version__.py
esrt/clients.py
esrt/cmd_base.py
esrt/cmd_es_bulk.py
esrt/cmd_es_info.py
esrt/cmd_es_ping.py
esrt/cmd_es_request.py
esrt/cmd_es_scan.py
esrt/cmd_es_search.py
esrt/cmd_es_sql.py
esrt/exceptions.py
esrt/handlers.py
esrt/logging_.py
esrt/main.py
esrt/py.typed
esrt/typealiases.py
esrt-8.7.0.dist-info/METADATA
esrt-8.7.0.dist-info/WHEEL
esrt-8.7.0.dist-info/entry_points.txt
esrt-8.7.0.dist-info/RECORD
