Metadata-Version: 2.4
Name: esrt
Version: 8.7.0
Classifier: Programming Language :: Python :: 3 :: Only
Classifier: Programming Language :: Python :: 3.9
Classifier: Programming Language :: Python :: 3.10
Classifier: Programming Language :: Python :: 3.11
Classifier: Programming Language :: Python :: 3.12
Classifier: Programming Language :: Python :: 3.13
Requires-Python: >=3.9
Requires-Dist: certifi>=2025.8.3
Requires-Dist: elasticsearch==6.8.2
Requires-Dist: ipython>=8.18.1
Requires-Dist: pydantic-settings>=2.8.1
Requires-Dist: pydantic>=2.10.6
Requires-Dist: rich>=13.9.4
Requires-Dist: typing-extensions>=4.12.2
Requires-Dist: uvicorn>=0.2.14
